GAdmin/__init__.py
GAdmin/cli.py
GAdmin-0.1.1.dist-info/LICENSE
GAdmin-0.1.1.dist-info/METADATA
GAdmin-0.1.1.dist-info/WHEEL
GAdmin-0.1.1.dist-info/entry_points.txt
GAdmin-0.1.1.dist-info/top_level.txt
GAdmin-0.1.1.dist-info/RECORD
