Metadata-Version: 2.1
Name: GAdmin
Version: 0.1.1
Summary: CLI tool for quick GitHub repository management and viewing.
Home-page: https://github.com/JaredTPonting/GHManager
Author: Jared T Ponting
Author-email: jaredtponting@gmail.com
Classifier: Programming Language :: Python :: 3
Requires-Python: >3.6
License-File: LICENSE
Requires-Dist: requests
Requires-Dist: pyyaml
